azure/core/tracing/ext/opencensus_span/__init__.py
azure/core/tracing/ext/opencensus_span/_version.py
azure/core/tracing/ext/opencensus_span/py.typed
azure_core_tracing_opencensus-1.0.0b10.dist-info/LICENSE
azure_core_tracing_opencensus-1.0.0b10.dist-info/METADATA
azure_core_tracing_opencensus-1.0.0b10.dist-info/WHEEL
azure_core_tracing_opencensus-1.0.0b10.dist-info/top_level.txt
azure_core_tracing_opencensus-1.0.0b10.dist-info/RECORD
