Metadata-Version: 2.1
Name: azure-core-tracing-opencensus
Version: 1.0.0b10
Summary: Microsoft Azure Azure Core Opencensus plugin Library for Python
Home-page: https://github.com/Azure/azure-sdk-for-python/tree/main/sdk/core/azure-core-tracing-opencensus
Author: Microsoft Corporation
Author-email: azpysdkhelp@microsoft.com
License: MIT License
Keywords: azure,azure sdk
Classifier: Development Status :: 7 - Inactive
Classifier: Programming Language :: Python
Classifier: Programming Language :: Python :: 3 :: Only
Classifier: Programming Language :: Python :: 3
Classifier: Programming Language :: Python :: 3.8
Classifier: Programming Language :: Python :: 3.9
Classifier: Programming Language :: Python :: 3.10
Classifier: Programming Language :: Python :: 3.11
Classifier: Programming Language :: Python :: 3.12
Classifier: License :: OSI Approved :: MIT License
Requires-Python: >=3.8
License-File: LICENSE
Requires-Dist: opencensus >=0.6.0
Requires-Dist: opencensus-ext-azure >=0.3.1
Requires-Dist: opencensus-ext-threading
Requires-Dist: azure-core >=1.13.0
